auto_prefetch/__init__.py
auto_prefetch/py.typed
django_auto_prefetch-1.13.0.dist-info/licenses/LICENSE
django_auto_prefetch-1.13.0.dist-info/METADATA
django_auto_prefetch-1.13.0.dist-info/WHEEL
django_auto_prefetch-1.13.0.dist-info/top_level.txt
django_auto_prefetch-1.13.0.dist-info/RECORD
