Metadata-Version: 2.4
Name: django-auto-prefetch
Version: 1.13.0
Summary: Automatically prefetch foreign key values as needed.
Author-email: Gordon Wrigley <gordon.wrigley@gmail.com>
License-Expression: BSD-3-Clause
Project-URL: Changelog, https://github.com/tolomea/django-auto-prefetch/blob/main/CHANGELOG.rst
Project-URL: Repository, https://github.com/tolomea/django-auto-prefetch
Classifier: Development Status :: 5 - Production/Stable
Classifier: Framework :: Django :: 4.2
Classifier: Framework :: Django :: 5.0
Classifier: Framework :: Django :: 5.1
Classifier: Framework :: Django :: 5.2
Classifier: Intended Audience :: Developers
Classifier: Natural Language :: English
Classifier: Operating System :: OS Independent
Classifier: Programming Language :: Python :: 3 :: Only
Classifier: Programming Language :: Python :: 3.9
Classifier: Programming Language :: Python :: 3.10
Classifier: Programming Language :: Python :: 3.11
Classifier: Programming Language :: Python :: 3.12
Classifier: Programming Language :: Python :: 3.13
Classifier: Programming Language :: Python :: 3.14
Classifier: Programming Language :: Python :: Implementation :: CPython
Classifier: Typing :: Typed
Requires-Python: >=3.9
License-File: LICENSE
Requires-Dist: django>=4.2
Dynamic: license-file
